quick_email/__init__.py
quick_email/builder.py
quick_email/sender.py
quick_email-0.5.0.dist-info/LICENSE
quick_email-0.5.0.dist-info/METADATA
quick_email-0.5.0.dist-info/WHEEL
quick_email-0.5.0.dist-info/top_level.txt
quick_email-0.5.0.dist-info/RECORD
