Metadata-Version: 2.1
Name: quick-email
Version: 0.5.0
Summary: Quick-and-Dirty Email Sender
Home-page: https://github.com/murrple-1/quick-email-python
Author: Murray Christopherson
Author-email: murraychristopherson@gmail.com
License: UNKNOWN
Keywords: mail email smtp easy
Platform: UNKNOWN
Classifier: Development Status :: 4 - Beta
Classifier: Intended Audience :: Developers
Classifier: Topic :: Software Development :: Libraries
Classifier: License :: OSI Approved :: MIT License
Classifier: Programming Language :: Python :: 3
Classifier: Programming Language :: Python :: 3.5
Classifier: Programming Language :: Python :: 3.6
Requires-Dist: six
